{
    "00060265": {
        "article_title": "Техноплекс 1180*580*100 0,2737м3, 2,7376м2, 4 плиты",
        "article_desc": "Код товара 00060265",
        "article_price": "Цена после регистрации    руб.     за 1        10 810         руб.  за 1",
        "article_url": "https://keramix-oskol.ru/catalog/tekhnopleks/None"
    },
    "00051982": {
        "article_title": "Техноплекс 1180*580*30L",
        "article_desc": "Код товара 00051982",
        "article_price": "Цена после регистрации\r\n                            \n\n \r\n                                 руб.                                за 1 \n\n\n\r\n                            230                            \r\n                                 руб.                                за 1",
        "article_url": "https://keramix-oskol.ru/catalog/tekhnopleks/None"
    },
    "00035832": {
        "article_title": "Техноплекс 1180*580*30L 0.267м3 13 плит 8,9 кв2",
        "article_desc": "Код товара 00035832",
        "article_price": "Цена после регистрации\r\n                            \n\n \r\n                                 руб.                                за 1 \n\n\n\r\n                            11 100                            \r\n                                 руб.                                за 1",
        "article_url": "https://keramix-oskol.ru/catalog/tekhnopleks/None"
    },
    "00036001": {
        "article_title": "Техноплекс 1180*580*40 0.274м3,6,84м2 10 пли",
        "article_desc": "Код товара 00036001",
        "article_price": "Цена после регистрации\r\n                            \n\n \r\n                                 руб.                                за 1 \n\n\n\r\n                            11 070                            \r\n                                 руб.                                за 1",
        "article_url": "https://keramix-oskol.ru/catalog/tekhnopleks/None"
    },
    "00175768": {
        "article_title": "Техноплекс 1180*580*50 0.2053м3 , 4,1064 м2, 6 плит (352)",
        "article_desc": "Код товара 00175768",
        "article_price": "10 350                        \n\r\n                             руб.                            за 1",
        "article_url": "https://keramix-oskol.ru/catalog/tekhnopleks/None"
    },
    "00122736": {
        "article_title": "Техноплекс 1180*580*50 0.27376м3 , 5,4752 м2, 8 плит (352)",
        "article_desc": "Код товара 00122736",
        "article_price": "Цена после регистрации\r\n                            \n\n \r\n                                 руб.                                за 1 \n\n\n\r\n                            10 350                            \r\n                                 руб.                                за 1",
        "article_url": "https://keramix-oskol.ru/catalog/tekhnopleks/None"
    },
    "00098611": {
        "article_title": "Техноплекс 1200*600*20",
        "article_desc": "Код товара 00098611",
        "article_price": "Цена после регистрации\r\n                            \n\n \r\n                                 руб.                                за 1 \n\n\n\r\n                            165                            \r\n                                 руб.                                за 1",
        "article_url": "https://keramix-oskol.ru/catalog/tekhnopleks/None"
    },
    "00095233": {
        "article_title": "Техноплекс 1200*600*20 (14,4 м2, 0,288 м3, 20 шт )",
        "article_desc": "Код товара 00095233",
        "article_price": "Цена после регистрации\r\n                            \n\n \r\n                                 руб.                                за 1 \n\n\n\r\n                            11 410                            \r\n                                 руб.                                за 1",
        "article_url": "https://keramix-oskol.ru/catalog/tekhnopleks/None"
    },
    "00051983": {
        "article_title": "Утеплитель Техноплекс 1180*580*50L",
        "article_desc": "Код товара 00051983",
        "article_price": "Цена после регистрации\r\n                            \n\n \r\n                                 руб.                                за 1 \n\n\n\r\n                            355                            \r\n                                 руб.                                за 1",
        "article_url": "https://keramix-oskol.ru/catalog/tekhnopleks/None"
    },
    "00141258": {
        "article_title": "PIR Плита ТЕХНОНИКОЛЬ (CXM\\CXM) с L кромкой  2385*1185*50 (22,61м2; 1,13м3, 8 плит)",
        "article_desc": "Код товара 00141258",
        "article_price": "725                        \n\r\n                             руб.                            за 1",
        "article_url": "https://keramix-oskol.ru/catalog/tekhnopleks/None"
    },
    "00153025": {
        "article_title": "Техноплекс 1180*580*100",
        "article_desc": "Код товара 00153025",
        "article_price": "Цена после регистрации\r\n                            \n\n \r\n                                 руб.                                за 1 \n\n\n\r\n                            745                            \r\n                                 руб.                                за 1",
        "article_url": "https://keramix-oskol.ru/catalog/tekhnopleks/None"
    },
    "00183003": {
        "article_title": "Техноплекс 1180*580*30L НЕКОНДИЦИЯ",
        "article_desc": "Код товара 00183003",
        "article_price": "172                        \n\r\n                             руб.                            за 1",
        "article_url": "https://keramix-oskol.ru/catalog/tekhnopleks/None"
    }
}